Metadata-Version: 1.0
Name: distributions-mwi
Version: 0.1
Summary: Gaussian and binomial distributions
Home-page: https://github.com/mwinterde/Putting-Code-On-PiPy
Author: Marcus Winter
Author-email: marcus.winter.privat@gmail.com
License: UNKNOWN
Platform: UNKNOWN
